sig2cli/__init__.py
sig2cli/sig2cli.py
sig2cli-0.1.3.dist-info/DESCRIPTION.rst
sig2cli-0.1.3.dist-info/METADATA
sig2cli-0.1.3.dist-info/RECORD
sig2cli-0.1.3.dist-info/WHEEL
sig2cli-0.1.3.dist-info/metadata.json
sig2cli-0.1.3.dist-info/top_level.txt
