Metadata-Version: 2.0
Name: sig2cli
Version: 0.1.3
Summary: Turn function signatures into Command Line Interfaces
Home-page: https://github.com/PaoloSarti/sig2cli
Author: Paolo Sarti
Author-email: paolo.sarti@gmail.com
License: MIT
Platform: UNKNOWN
Requires-Dist: funcsigs
